src/__init__.py
src/cisco_mce_files.py
cisco_api_files_mxoran-0.0.1.dist-info/LICENSE
cisco_api_files_mxoran-0.0.1.dist-info/METADATA
cisco_api_files_mxoran-0.0.1.dist-info/WHEEL
cisco_api_files_mxoran-0.0.1.dist-info/top_level.txt
cisco_api_files_mxoran-0.0.1.dist-info/RECORD
